LICENSE.rst
MANIFEST.in
README.md
setup.cfg
setup.py
KnitScript/__init__.py
KnitScript/interpret.py
KnitScript.egg-info/PKG-INFO
KnitScript.egg-info/SOURCES.txt
KnitScript.egg-info/dependency_links.txt
KnitScript.egg-info/entry_points.txt
KnitScript.egg-info/requires.txt
KnitScript.egg-info/top_level.txt
KnitScript/knit_graphs/Knit_Graph.py
KnitScript/knit_graphs/Loop.py
KnitScript/knit_graphs/Pull_Direction.py
KnitScript/knit_graphs/Yarn.py
KnitScript/knit_graphs/__init__.py
KnitScript/knit_script_interpreter/Knit_Script_Interpreter.py
KnitScript/knit_script_interpreter/__init__.py
KnitScript/knit_script_interpreter/header_structure.py
KnitScript/knit_script_interpreter/knit_script.pg
KnitScript/knit_script_interpreter/knit_script_actions.py
KnitScript/knit_script_interpreter/knit_script_context.py
KnitScript/knit_script_interpreter/run_dat_compiler.py
KnitScript/knit_script_interpreter/variable_scope.py
KnitScript/knit_script_interpreter/expressions/Gauge_Expression.py
KnitScript/knit_script_interpreter/expressions/__init__.py
KnitScript/knit_script_interpreter/expressions/accessors.py
KnitScript/knit_script_interpreter/expressions/carrier.py
KnitScript/knit_script_interpreter/expressions/direction.py
KnitScript/knit_script_interpreter/expressions/expressions.py
KnitScript/knit_script_interpreter/expressions/formatted_string.py
KnitScript/knit_script_interpreter/expressions/function_expressions.py
KnitScript/knit_script_interpreter/expressions/instruction_expression.py
KnitScript/knit_script_interpreter/expressions/list_expression.py
KnitScript/knit_script_interpreter/expressions/machine_accessor.py
KnitScript/knit_script_interpreter/expressions/needle_expression.py
KnitScript/knit_script_interpreter/expressions/needle_set_expression.py
KnitScript/knit_script_interpreter/expressions/not_expression.py
KnitScript/knit_script_interpreter/expressions/operator_expressions.py
KnitScript/knit_script_interpreter/expressions/values.py
KnitScript/knit_script_interpreter/expressions/variables.py
KnitScript/knit_script_interpreter/expressions/xfer_pass_racking.py
KnitScript/knit_script_interpreter/statements/Assertion.py
