Metadata-Version: 2.1
Name: KnitScript
Version: 0.1
Summary: Interpreter from KnitScript to Knitout Instructions
Home-page: https://github.khoury.northeastern.edu/mhofmann/KnitScript
Author: Megan Hofmann
Author-email: m.hofmann@northeastern.edu
License: MIT
Platform: UNKNOWN
License-File: LICENSE.rst
